ddtrace/context.py
ddtrace/provider.py
ddtrace/sampler.py
ddtrace/util.py
ddtrace/payload.py
ddtrace/span.py
ddtrace/api.py
ddtrace/__init__.py
ddtrace/_worker.py
ddtrace/constants.py
ddtrace/compat.py
ddtrace/filters.py
ddtrace/helpers.py
ddtrace/monkey.py
ddtrace/tracer.py
ddtrace/encoding.py
ddtrace/pin.py
ddtrace/internal/hostname.py
ddtrace/internal/__init__.py
ddtrace/internal/writer.py
ddtrace/internal/context_manager.py
ddtrace/internal/import_hooks.py
ddtrace/internal/logger.py
ddtrace/internal/rate_limiter.py
ddtrace/internal/runtime/runtime_metrics.py
ddtrace/internal/runtime/tag_collectors.py
ddtrace/internal/runtime/collector.py
ddtrace/internal/runtime/__init__.py
ddtrace/internal/runtime/constants.py
ddtrace/internal/runtime/lightstep_metrics.py
ddtrace/internal/runtime/container.py
ddtrace/internal/runtime/metric_collectors.py
ddtrace/utils/wrappers.py
ddtrace/utils/importlib.py
ddtrace/utils/config.py
ddtrace/utils/deprecation.py
ddtrace/utils/__init__.py
ddtrace/utils/formats.py
ddtrace/utils/time.py
ddtrace/utils/http.py
ddtrace/utils/merge.py
ddtrace/utils/hook.py
ddtrace/utils/attrdict.py
ddtrace/propagation/utils.py
ddtrace/propagation/__init__.py
ddtrace/propagation/http.py
ddtrace/propagation/b3.py
ddtrace/propagation/datadog.py
ddtrace/settings/config.py
ddtrace/settings/hooks.py
ddtrace/settings/__init__.py
ddtrace/settings/http.py
ddtrace/settings/exceptions.py
ddtrace/settings/integration.py
ddtrace/opentracer/settings.py
ddtrace/opentracer/span.py
ddtrace/opentracer/utils.py
ddtrace/opentracer/__init__.py
ddtrace/opentracer/tags.py
ddtrace/opentracer/helpers.py
ddtrace/opentracer/tracer.py
ddtrace/opentracer/span_context.py
ddtrace/opentracer/propagation/__init__.py
ddtrace/opentracer/propagation/binary.py
ddtrace/opentracer/propagation/http.py
ddtrace/opentracer/propagation/text.py
ddtrace/opentracer/propagation/propagator.py
ddtrace/bootstrap/__init__.py
ls_trace-0.2.1.dist-info/LICENSE
ls_trace-0.2.1.dist-info/top_level.txt
ls_trace-0.2.1.dist-info/WHEEL
ls_trace-0.2.1.dist-info/RECORD
ls_trace-0.2.1.dist-info/METADATA
ls_trace-0.2.1.dist-info/entry_points.txt
ls_trace-0.2.1.dist-info/LICENSE.Apache
ls_trace-0.2.1.dist-info/NOTICE
ls_trace-0.2.1.dist-info/LICENSE.BSD3
