Metadata-Version: 2.1
Name: ls-trace
Version: 0.2.1
Summary: Datadog tracing code
Home-page: https://github.com/lightstep/ls-trace-py
Author: LightStep
Author-email: support@lightstep.com
License: BSD
Platform: UNKNOWN
Classifier: Programming Language :: Python
Classifier: Programming Language :: Python :: 2.7
Classifier: Programming Language :: Python :: 3.4
Classifier: Programming Language :: Python :: 3.5
Classifier: Programming Language :: Python :: 3.6
Classifier: Programming Language :: Python :: 3.7
Classifier: Programming Language :: Python :: 3.8
Requires-Dist: backoff (>=1.8.0)
Requires-Dist: googleapis-common-protos (>=1.51.0)
Requires-Dist: msgpack (>=0.5.0)
Requires-Dist: protobuf (>=3.11.3)
Requires-Dist: requests
Requires-Dist: enum34 ; python_version < "3.4"
Requires-Dist: funcsigs (>=1.0.0) ; python_version == "2.7"
Provides-Extra: opentracing
Requires-Dist: opentracing (>=2.0.0) ; extra == 'opentracing'
Provides-Extra: profile
Requires-Dist: protobuf (>=3) ; extra == 'profile'
Requires-Dist: intervaltree ; extra == 'profile'
